jmespathutils/__init__.py
jmespathutils/functions.py
jmespathutils/jmespathutils.py
jmespathutils-0.1.3.dist-info/AUTHORS.rst
jmespathutils-0.1.3.dist-info/LICENSE
jmespathutils-0.1.3.dist-info/METADATA
jmespathutils-0.1.3.dist-info/WHEEL
jmespathutils-0.1.3.dist-info/top_level.txt
jmespathutils-0.1.3.dist-info/RECORD
